{
  "tanggal_rencana": "2026-07-24",
  "generated_at": "2026-07-23T00:43:33.910Z",
  "vehicles": [
    {
      "id": 1,
      "name": "Mobil 1",
      "total": 45600000,
      "stops": [
        {
          "cc": "917102300301373064",
          "invoice": 150000
        },
        {
          "cc": "917102300201314766",
          "invoice": 3525000
        },
        {
          "cc": "917102300301280026",
          "invoice": 4275000
        },
        {
          "cc": "917102200300864587",
          "invoice": 2025000
        },
        {
          "cc": "917102100301316052",
          "invoice": 275000
        },
        {
          "cc": "917102100100864332",
          "invoice": 3400000
        },
        {
          "cc": "917102100501247093",
          "invoice": 2400000
        },
        {
          "cc": "917102000301311651",
          "invoice": 4900000
        },
        {
          "cc": "910717100301234984",
          "invoice": 6400000
        },
        {
          "cc": "910717100501255128",
          "invoice": 5650000
        },
        {
          "cc": "910607001901322952",
          "invoice": 525000
        },
        {
          "cc": "917102001101264379",
          "invoice": 1900000
        },
        {
          "cc": "917102200301311678",
          "invoice": 5025000
        },
        {
          "cc": "917102200301256582",
          "invoice": 5150000
        }
      ]
    },
    {
      "id": 2,
      "name": "Mobil 2",
      "total": 43825000,
      "stops": [
        {
          "cc": "917102200500864548",
          "invoice": 4775000
        },
        {
          "cc": "917102300501203397",
          "invoice": 4400000
        },
        {
          "cc": "917102100401264578",
          "invoice": 5275000
        },
        {
          "cc": "917102300101234986",
          "invoice": 6150000
        },
        {
          "cc": "917102300101220234",
          "invoice": 6025000
        },
        {
          "cc": "910717000401245595",
          "invoice": 5525000
        },
        {
          "cc": "917102200401241031",
          "invoice": 5900000
        },
        {
          "cc": "917102100401258584",
          "invoice": 5775000
        }
      ]
    },
    {
      "id": 3,
      "name": "Mobil 3",
      "total": 39700000,
      "stops": [
        {
          "cc": "917102001301304336",
          "invoice": 6275000
        },
        {
          "cc": "917102100501417709",
          "invoice": 3650000
        },
        {
          "cc": "917102300501315160",
          "invoice": 4025000
        },
        {
          "cc": "917102300201314770",
          "invoice": 4650000
        },
        {
          "cc": "917102100901397574",
          "invoice": 4150000
        },
        {
          "cc": "917102100300864393",
          "invoice": 2275000
        },
        {
          "cc": "917102100501311489",
          "invoice": 1275000
        },
        {
          "cc": "917102000301105205",
          "invoice": 3900000
        },
        {
          "cc": "917102001201451239",
          "invoice": 900000
        },
        {
          "cc": "917102001201367179",
          "invoice": 1025000
        },
        {
          "cc": "917102001301371833",
          "invoice": 3775000
        },
        {
          "cc": "917102001301033830",
          "invoice": 775000
        },
        {
          "cc": "917102001301371832",
          "invoice": 3025000
        }
      ]
    },
    {
      "id": 4,
      "name": "Mobil 4",
      "total": 44425000,
      "stops": [
        {
          "cc": "910717000501259031",
          "invoice": 6525000
        },
        {
          "cc": "910717000100863860",
          "invoice": 2900000
        },
        {
          "cc": "910717000400863737",
          "invoice": 1525000
        },
        {
          "cc": "910717000401355382",
          "invoice": 2150000
        },
        {
          "cc": "910717000101234988",
          "invoice": 5400000
        },
        {
          "cc": "910717000400863818",
          "invoice": 2775000
        },
        {
          "cc": "910717001601440905",
          "invoice": 4525000
        },
        {
          "cc": "910717000101360766",
          "invoice": 3275000
        },
        {
          "cc": "917102300301440904",
          "invoice": 650000
        },
        {
          "cc": "910712100401460158",
          "invoice": 1650000
        },
        {
          "cc": "910712100200864010",
          "invoice": 1400000
        },
        {
          "cc": "910712100100864004",
          "invoice": 3150000
        },
        {
          "cc": "910712001000864019",
          "invoice": 1775000
        },
        {
          "cc": "910717000400863705",
          "invoice": 2525000
        },
        {
          "cc": "910712000700864056",
          "invoice": 2650000
        },
        {
          "cc": "917101000701311470",
          "invoice": 400000
        },
        {
          "cc": "910606000101455105",
          "invoice": 1150000
        }
      ]
    }
  ]
}